LICENSE
README.rst
setup.cfg
setup.py
jit_open/__init__.py
jit_open/jit_open.py
jit_open/open_wrapper.py
jit_open.egg-info/PKG-INFO
jit_open.egg-info/SOURCES.txt
jit_open.egg-info/dependency_links.txt
jit_open.egg-info/entry_points.txt
jit_open.egg-info/requires.txt
jit_open.egg-info/top_level.txt