Metadata-Version: 2.1
Name: jit-open
Version: 1.0.2
Summary: Just in time open files
Home-page: https://github.com/jfjlaros/jit-open
Author: Jeroen F.J. Laros
Author-email: J.F.J.Laros@lumc.nl
License: MIT
Keywords: bioinformatics
Platform: UNKNOWN
Classifier: Intended Audience :: Science/Research
Classifier: Intended Audience :: Developers
Classifier: Operating System :: OS Independent
Classifier: Programming Language :: Python
Classifier: Topic :: Scientific/Engineering
Provides-Extra: tests
